<?xml version="1.0" encoding="utf-8" ?><dwsync><file name="frownie.png" server="clusterftp01.evxonline.com//httpdocs/" local="3511484426" remote="12117168032" /><file name="icon_arrow.gif" server="clusterftp01.evxonline.com//httpdocs/" local="3497371342" remote="12117168032" /><file name="icon_biggrin.gif" server="clusterftp01.evxonline.com//httpdocs/" local="3497371342" remote="12117168032" /><file name="icon_confused.gif" server="clusterftp01.evxonline.com//httpdocs/" local="3497371342" remote="12117168032" /><file name="icon_cool.gif" server="clusterftp01.evxonline.com//httpdocs/" local="3497371342" remote="12117168032" /><file name="icon_cry.gif" server="clusterftp01.evxonline.com//httpdocs/" local="3497371342" remote="12117168032" /><file name="icon_eek.gif" server="clusterftp01.evxonline.com//httpdocs/" local="3497371342" remote="12117168032" /><file name="icon_evil.gif" server="clusterftp01.evxonline.com//httpdocs/" local="3497371342" remote="12117168032" /><file name="icon_exclaim.gif" server="clusterftp01.evxonline.com//httpdocs/" local="3497371342" remote="12117168032" /><file name="icon_idea.gif" server="clusterftp01.evxonline.com//httpdocs/" local="3497371342" remote="12117168032" /><file name="icon_lol.gif" server="clusterftp01.evxonline.com//httpdocs/" local="3497371342" remote="12117168032" /><file name="icon_mad.gif" server="clusterftp01.evxonline.com//httpdocs/" local="3497371342" remote="12117168032" /><file name="icon_mrgreen.gif" server="clusterftp01.evxonline.com//httpdocs/" local="3497371342" remote="12117168032" /><file name="icon_neutral.gif" server="clusterftp01.evxonline.com//httpdocs/" local="3497371342" remote="12117168032" /><file name="icon_question.gif" server="clusterftp01.evxonline.com//httpdocs/" local="3497371342" remote="12117168032" /><file name="icon_razz.gif" server="clusterftp01.evxonline.com//httpdocs/" local="3497371342" remote="12117168032" /><file name="icon_redface.gif" server="clusterftp01.evxonline.com//httpdocs/" local="3497371342" remote="12117168032" /><file name="icon_rolleyes.gif" server="clusterftp01.evxonline.com//httpdocs/" local="3497371342" remote="12117168032" /><file name="icon_sad.gif" server="clusterftp01.evxonline.com//httpdocs/" local="3497371342" remote="12117168032" /><file name="icon_smile.gif" server="clusterftp01.evxonline.com//httpdocs/" local="3497371342" remote="12117168032" /><file name="icon_surprised.gif" server="clusterftp01.evxonline.com//httpdocs/" local="3497371342" remote="12117168032" /><file name="icon_twisted.gif" server="clusterftp01.evxonline.com//httpdocs/" local="3497371342" remote="12117168032" /><file name="icon_wink.gif" server="clusterftp01.evxonline.com//httpdocs/" local="3497371342" remote="12117168032" /><file name="mrgreen.png" server="clusterftp01.evxonline.com//httpdocs/" local="3511484426" remote="12117168032" /><file name="rolleyes.png" server="clusterftp01.evxonline.com//httpdocs/" local="3511484426" remote="12117168032" /><file name="simple-smile.png" server="clusterftp01.evxonline.com//httpdocs/" local="3511484426" remote="12117168032" /></dwsync>